[
    {
        "userData": "风行-zi'xi'ui",
        "today": "2020年03月09日",
        "user": "风行",
        "signature": "不要依靠想象去理解世界",
        "id": 1583751008495,
        "table": [
            {
                "studyDate": "20200309",
                "segmentation": "18:37 - 18:50",
                "minuteDuration": 13,
                "hourDuration": 0.22,
                "studyContent": "写作业"
            },
            {
                "studyDate": "20200309",
                "segmentation": "21:37 - 23:00",
                "minuteDuration": 83,
                "hourDuration": 1.38,
                "studyContent": "写作业"
            },
            {
                "studyDate": "20200309",
                "segmentation": "23:13 - 23:30",
                "minuteDuration": 17,
                "hourDuration": 0.28,
                "studyContent": "看 chat"
            }
        ]
    },
    {
        "userData": "life-123",
        "today": "2020年03月09日",
        "user": "life",
        "signature": "只做两件事",
        "id": 1583725413492,
        "table": [
            {
                "studyDate": "20200309",
                "segmentation": "11:21 - 11:43",
                "minuteDuration": 22,
                "hourDuration": 0.37,
                "studyContent": "复习一下 webpack （放弃了）"
            },
            {
                "studyDate": "20200309",
                "segmentation": "11:43 - 13:01",
                "minuteDuration": 78,
                "hourDuration": 1.3,
                "studyContent": "面试准备-刷面试题"
            },
            {
                "studyDate": "20200309",
                "segmentation": "14:35 - 15:54",
                "minuteDuration": 79,
                "hourDuration": 1.32,
                "studyContent": "面试准备-论坛面经"
            },
            {
                "studyDate": "20200309",
                "segmentation": "17:48 - 18:19",
                "minuteDuration": 31,
                "hourDuration": 0.52,
                "studyContent": "面试准备-论坛面经"
            }
        ]
    },
    {
        "userData": "猫钰钰-19931124",
        "today": "2020年03月09日",
        "user": "猫钰钰",
        "signature": "",
        "id": 1583697749306,
        "table": [
            {
                "studyDate": "20200309",
                "segmentation": "03:02 - 04:02",
                "minuteDuration": 60,
                "hourDuration": 1,
                "studyContent": "b站入门课"
            },
            {
                "studyDate": "20200309",
                "segmentation": "12:11 - 14:22",
                "minuteDuration": 131,
                "hourDuration": 2.18,
                "studyContent": "看Why We Sleep"
            },
            {
                "studyDate": "20200309",
                "segmentation": "15:08 - 15:45",
                "minuteDuration": 37,
                "hourDuration": 0.62,
                "studyContent": "看Why We Sleep"
            }
        ]
    }
]