[
    {
        "userData": "life-123",
        "today": "2020年04月06日",
        "user": "life",
        "signature": "",
        "id": 1586104588378,
        "table": [
            {
                "studyDate": "20200406",
                "segmentation": "23:09 - 00:36",
                "minuteDuration": 87,
                "hourDuration": 1.45,
                "studyContent": "axe - 重做作业17-2，看 chat 调整贴图"
            },
            {
                "studyDate": "20200406",
                "segmentation": "09:02 - 09:32",
                "minuteDuration": 30,
                "hourDuration": 0.5,
                "studyContent": "自习室 - 调整样式"
            },
            {
                "studyDate": "20200406",
                "segmentation": "09:43 - 10:54",
                "minuteDuration": 71,
                "hourDuration": 1.18,
                "studyContent": "axe - 看 chat"
            },
            {
                "studyDate": "20200406",
                "segmentation": "11:16 - 12:02",
                "minuteDuration": 46,
                "hourDuration": 0.77,
                "studyContent": "axe - 看 chat， 画 cube"
            }
        ]
    }
]